nonebot_plugin_warframe_mode/__init__.py
nonebot_plugin_warframe_mode/data_source.py
nonebot_plugin_warframe_mode-1.1.0.dist-info/LICENSE
nonebot_plugin_warframe_mode-1.1.0.dist-info/METADATA
nonebot_plugin_warframe_mode-1.1.0.dist-info/WHEEL
nonebot_plugin_warframe_mode-1.1.0.dist-info/top_level.txt
nonebot_plugin_warframe_mode-1.1.0.dist-info/RECORD
