Metadata-Version: 2.1
Name: nonebot-plugin-warframe-mode
Version: 1.1.0
Summary: 基于nonebot2的WM市场查询的插件
Home-page: https://github.com/mmxd12/nonebot_plugin_warframe_mode
Author: mmxd12
Author-email: mys0627@outlook.com
Classifier: Programming Language :: Python :: 3.11
Classifier: License :: OSI Approved :: MIT License
Classifier: Operating System :: OS Independent
License-File: LICENSE
Requires-Dist: nonebot2 (>=2.0.0rc3)
Requires-Dist: nonebot-adapter-onebot (>=2.2.1)
Requires-Dist: httpx (>=0.23.3)
